deviousq/__init__.py
deviousq-0.0.3.dist-info/LICENSE
deviousq-0.0.3.dist-info/METADATA
deviousq-0.0.3.dist-info/WHEEL
deviousq-0.0.3.dist-info/entry_points.txt
deviousq-0.0.3.dist-info/top_level.txt
deviousq-0.0.3.dist-info/RECORD
