Metadata-Version: 2.1
Name: deviousq
Version: 0.0.3
Summary: DeviantArt RSS API querying utility
Author-email: Anders Feder <anders.feder.83@gmail.com>
License: MIT
Project-URL: Homepage, https://gitlab.com/afeder/deviousq
Project-URL: Repository, https://gitlab.com/afeder/deviousq.git
Keywords: DeviantArt,cli
Classifier: Development Status :: 2 - Pre-Alpha
Classifier: License :: OSI Approved :: MIT License
Classifier: Programming Language :: Python :: 3
Classifier: Programming Language :: Python :: 3.6
Classifier: Operating System :: OS Independent
Classifier: Environment :: Console
Classifier: Intended Audience :: End Users/Desktop
Classifier: Topic :: Internet :: WWW/HTTP
Requires-Python: >=3.6
License-File: LICENSE
Requires-Dist: aiohttp==3.10.0
Requires-Dist: python-dateutil==2.8.2
